{
  "kind": "collectionType",
  "collectionName": "pessoa_situacao_ruas",
  "info": {
    "singularName": "pessoa-situacao-rua",
    "pluralName": "pessoa-situacao-ruas",
    "displayName": "pessoa_situacao_ruas"
  },
  "options": {
    "draftAndPublish": true
  },
  "pluginOptions": {},
  "attributes": {
    "pes_id": {
      "type": "uid"
    },
    "pes_nome": {
      "type": "string"
    },
    "pes_data_nasc": {
      "type": "date"
    },
    "pes_sexo": {
      "type": "integer"
    }
  }
}
